orgee_roam/__init__.py
orgee_roam/const.py
orgee_roam/py.typed
orgee_roam/zettel.py
orgee_roam/zettelkasten.py
orgee_roam/zettels.py
orgee_roam/zk_func/__init__.py
orgee_roam/zk_func/finder_zettel.py
orgee_roam/zk_func/list_zettel.py
orgee_roam/zk_func/make_zettel.py
orgee_roam/zk_func/update_cache.py
orgee_roam-0.0.6.dist-info/METADATA
orgee_roam-0.0.6.dist-info/WHEEL
orgee_roam-0.0.6.dist-info/top_level.txt
orgee_roam-0.0.6.dist-info/zip-safe
orgee_roam-0.0.6.dist-info/RECORD
