Metadata-Version: 2.1
Name: orgee-roam
Version: 0.0.6
Summary: Tools to manage a org-roam zettelkasten
Home-page: https://github.com/chunglak/orgee-roam
Author: Alfred Leung
Author-email: chunglak@gmail.com
License: GPL-3.0-or-later
Requires-Python: >=3.10
Requires-Dist: python-slugify[unidecode]
Requires-Dist: orgee
Requires-Dist: kombini
